jtr2hashcat/__init__.py
jtr2hashcat/__main__.py
jtr2hashcat-0.0.1.dist-info/LICENSE
jtr2hashcat-0.0.1.dist-info/METADATA
jtr2hashcat-0.0.1.dist-info/WHEEL
jtr2hashcat-0.0.1.dist-info/top_level.txt
jtr2hashcat-0.0.1.dist-info/RECORD
