Metadata-Version: 2.1
Name: jtr2hashcat
Version: 0.0.1
Summary: Tool for finding hashcat hash-modes for hashes extracted by JohnTheRipper.
Author-email: Andrej Roštek <rostek@mail.muni.cz>
License: MIT License
Keywords: hashcat,jtr,johntheripper
Classifier: License :: OSI Approved :: MIT License
Classifier: Programming Language :: Python
Classifier: Programming Language :: Python :: 3
Requires-Python: >=3.10
License-File: LICENSE
Provides-Extra: dev
Requires-Dist: black ; extra == 'dev'
Requires-Dist: isort ; extra == 'dev'
Requires-Dist: pytest ; extra == 'dev'
